ria_toolkit_oss/__init__.py
ria_toolkit_oss/datatypes/__init__.py
ria_toolkit_oss/datatypes/annotation.py
ria_toolkit_oss/datatypes/datasets/__init__.py
ria_toolkit_oss/datatypes/datasets/dataset_builder.py
ria_toolkit_oss/datatypes/datasets/h5helpers.py
ria_toolkit_oss/datatypes/datasets/iq_dataset.py
ria_toolkit_oss/datatypes/datasets/license/__init__.py
ria_toolkit_oss/datatypes/datasets/license/dataset_license.py
ria_toolkit_oss/datatypes/datasets/radio_dataset.py
ria_toolkit_oss/datatypes/datasets/spect_dataset.py
ria_toolkit_oss/datatypes/datasets/split.py
ria_toolkit_oss/datatypes/recording.py
ria_toolkit_oss/io/__init__.py
ria_toolkit_oss/io/recording.py
ria_toolkit_oss/sdr/__init__.py
ria_toolkit_oss/sdr/_external/libhackrf.py
ria_toolkit_oss/sdr/blade.py
ria_toolkit_oss/sdr/hackrf.py
ria_toolkit_oss/sdr/pluto.py
ria_toolkit_oss/sdr/sdr.py
ria_toolkit_oss/sdr/usrp.py
ria_toolkit_oss/transforms/__init__.py
ria_toolkit_oss/transforms/iq_augmentations.py
ria_toolkit_oss/transforms/iq_impairments.py
ria_toolkit_oss/utils/__init__.py
ria_toolkit_oss/utils/abstract_attribute.py
ria_toolkit_oss/utils/array_conversion.py
ria_toolkit_oss/viz/__init__.py
ria_toolkit_oss/viz/onnx.py
ria_toolkit_oss/viz/pytorch_model.py
ria_toolkit_oss/viz/pytorch_state_dict.py
ria_toolkit_oss/viz/radio_dataset.py
ria_toolkit_oss/viz/recording.py
ria_toolkit_oss-0.1.4.dist-info/LICENSE
ria_toolkit_oss-0.1.4.dist-info/METADATA
ria_toolkit_oss-0.1.4.dist-info/WHEEL
ria_toolkit_oss-0.1.4.dist-info/RECORD
