Metadata-Version: 2.3
Name: ria-toolkit-oss
Version: 0.1.4
Summary: An open-source version of the RIA Toolkit, including the fundamental tools to get started developing, testing, and deploying radio intelligence applications
License: AGPL-3.0-only
Keywords: radio,rf,sdr,software-defined radio,signal processing,wireless,machine learning,radio intelligence
Author: Qoherent Inc.
Author-email: info@qoherent.ai
Maintainer: Benjamin Chinnery
Maintainer-email: ben@qoherent.ai
Requires-Python: >=3.10
Classifier: Development Status :: 3 - Alpha
Classifier: Programming Language :: Python :: 3
Classifier: Intended Audience :: Science/Research
Classifier: Intended Audience :: Developers
Classifier: License :: OSI Approved :: GNU Affero General Public License v3
Classifier: Natural Language :: English
Classifier: Operating System :: POSIX :: Linux
Classifier: Topic :: Education
Classifier: Topic :: Scientific/Engineering
Classifier: Topic :: Communications :: Ham Radio
Classifier: Topic :: Software Development :: Libraries
Classifier: Typing :: Typed
Requires-Dist: h5py (>=3.14.0,<4.0.0)
Requires-Dist: numpy (==1.26.4)
Requires-Dist: pandas (>=2.3.2,<3.0.0)
Requires-Dist: plotly (>=6.3.0,<7.0.0)
Requires-Dist: pyzmq (>=27.1.0,<28.0.0)
Requires-Dist: quantiphy (>=2.20,<3.0)
Requires-Dist: scipy (<1.16)
Requires-Dist: sigmf (>=1.2.10,<2.0.0)
Project-URL: Issues Board, https://riahub.ai/qoherent/ria-toolkit-oss/issues
Project-URL: Qoherent, https://qoherent.ai/
Project-URL: Source, https://riahub.ai/qoherent/ria-toolkit-oss
